yolov4/__init__.py
yolov4/yolov4.py
yolov4/model/__init__.py
yolov4/model/convolution.py
yolov4/model/darknet.py
yolov4/model/loss.py
yolov4/model/neck.py
yolov4/model/prediction.py
yolov4/model/residual.py
yolov4/util/__init__.py
yolov4/util/file.py
yolov4/util/image_util.py
tf_yolov4-1.0.4.dist-info/LICENSE
tf_yolov4-1.0.4.dist-info/METADATA
tf_yolov4-1.0.4.dist-info/WHEEL
tf_yolov4-1.0.4.dist-info/top_level.txt
tf_yolov4-1.0.4.dist-info/zip-safe
tf_yolov4-1.0.4.dist-info/RECORD
