Metadata-Version: 2.1
Name: tf-yolov4
Version: 1.0.4
Summary: YOLOv4 implementation with Tensorflow 2
Home-page: https://github.com/Licht-T/tf-yolov4
License: MIT
Keywords: yolov4,tensorflow
Platform: UNKNOWN
Classifier: Topic :: Scientific/Engineering :: Image Recognition
Classifier: License :: OSI Approved :: MIT License
Classifier: Programming Language :: Python :: 3
Requires-Dist: pillow
Requires-Dist: tensorflow
Requires-Dist: tensorflow-addons
Requires-Dist: numpy
